substrate_python_api/__init__.py
substrate_python_api/metadata/V4_types.py
substrate_python_api/metadata/V5.py
substrate_python_api/metadata/V5_types.py
substrate_python_api/metadata/V6.py
substrate_python_api/metadata/V6_types.py
substrate_python_api/metadata/V7.py
substrate_python_api/metadata/V7_types.py
substrate_python_api/metadata/__init__.py
substrate_python_api/metadata/data.py
substrate_python_api/metadata/decode.py
substrate_python_api/metadata/decode_v0.py
substrate_python_api/metadata/decode_v4.py
substrate_python_api/metadata/decode_v5.py
substrate_python_api/metadata/decode_v6.py
substrate_python_api/metadata/decode_v7.py
substrate_python_api/metadata/get_metadata.py
substrate_python_api/metadata/metadata_types.py
substrate_python_api/sr25519/__init__.py
substrate_python_api/sr25519/sr25519.py
substrate_python_api/sr25519/test.py
substrate_python_api/sr25519/types.py
substrate_python_api/storage/__init__.py
substrate_python_api/storage/basic.py
substrate_python_api/storage/get_genesis.py
substrate_python_api/storage/storage.py
substrate_python_api/storage/types.py
substrate_python_api/tests/__init__.py
substrate_python_api/tests/chain.py
substrate_python_api/tests/config.py
substrate_python_api/tests/get_balance.py
substrate_python_api/tests/get_block_according_hash.py
substrate_python_api/tests/get_block_according_number.py
substrate_python_api/tests/get_block_hash.py
substrate_python_api/tests/get_block_number.py
substrate_python_api/tests/get_genesis_block.py
substrate_python_api/tests/get_latest_block.py
substrate_python_api/tests/get_metadata.py
substrate_python_api/tests/get_nonce.py
substrate_python_api/tests/get_storage.py
substrate_python_api/tests/get_storage_with_block_hash.py
substrate_python_api/tests/get_sudo_key.py
substrate_python_api/tests/get_system_events.py
substrate_python_api/tests/node_template.py
substrate_python_api/tests/request.py
substrate_python_api/tests/send_transfer.py
substrate_python_api/tests/state.py
substrate_python_api-0.0.2.dist-info/METADATA
substrate_python_api-0.0.2.dist-info/WHEEL
substrate_python_api-0.0.2.dist-info/top_level.txt
substrate_python_api-0.0.2.dist-info/RECORD
