Metadata-Version: 2.1
Name: substrate-python-api
Version: 0.0.2
Summary: python api for substrate
Home-page: https://github.com/juniuszhou/substrate-pyton-api
Author: junius
Author-email: junius.zhou@gmail.com
License: MIT Licence
Keywords: pip,substrate,api
Platform: any
